MANIFEST.in
README.txt
setup.py
docs/HISTORY.txt
docs/LICENSE.txt
src/silva/__init__.py
src/silva.app.sitemap.egg-info/PKG-INFO
src/silva.app.sitemap.egg-info/SOURCES.txt
src/silva.app.sitemap.egg-info/dependency_links.txt
src/silva.app.sitemap.egg-info/namespace_packages.txt
src/silva.app.sitemap.egg-info/not-zip-safe
src/silva.app.sitemap.egg-info/requires.txt
src/silva.app.sitemap.egg-info/top_level.txt
src/silva/app/__init__.py
src/silva/app/sitemap/__init__.py
src/silva/app/sitemap/configure.zcml
src/silva/app/sitemap/ftesting.zcml
src/silva/app/sitemap/interfaces.py
src/silva/app/sitemap/service.py
src/silva/app/sitemap/testing.py
src/silva/app/sitemap/utils.py
src/silva/app/sitemap/views.py
src/silva/app/sitemap/static/sitemap.png
src/silva/app/sitemap/tests/__init__.py
src/silva/app/sitemap/tests/test_buffered_streaming.py
src/silva/app/sitemap/tests/test_service.py
src/silva/app/sitemap/tests/test_sitemap_views.py
src/silva/app/sitemap/tests/data/photo.tif