Metadata-Version: 1.1
Name: silva.app.sitemap
Version: 1.0
Summary: Generate XML Sitemaps for Silva CMS
Home-page: https://github.com/silvacms/silva.app.sitemap
Author: Infrae
Author-email: info@infrae.com
License: BSD
Keywords: silva sitemap
Platform: UNKNOWN
Classifier: Framework :: Zope2
Classifier: License :: OSI Approved :: BSD License
Classifier: Programming Language :: Python
Classifier: Topic :: Software Development :: Libraries :: Python Modules
